[{"title":"REST API","path":"\/swagger.json","id":"all"},{"title":"- Auth","path":"\/swagger\/auth.swagger.json","id":"auth.swagger"},{"title":"- Billing","path":"\/swagger\/billing.swagger.json","id":"billing.swagger"},{"title":"- DNS","path":"\/swagger\/dns.swagger.json","id":"dns.swagger"},{"title":"- Domain","path":"\/swagger\/domain.swagger.json","id":"domain.swagger"},{"title":"- EasyDmarc","path":"\/swagger\/easydmarc.swagger.json","id":"easydmarc.swagger"},{"title":"- Email template","path":"\/swagger\/email-template.swagger.json","id":"email-template.swagger"},{"title":"- License","path":"\/swagger\/license.swagger.json","id":"license.swagger"},{"title":"- Reseller\/Customer","path":"\/swagger\/reseller-customer.swagger.json","id":"reseller-customer.swagger"},{"title":"- Spam Experts","path":"\/swagger\/spam-expert.swagger.json","id":"spam-expert.swagger"},{"title":"- SSL","path":"\/swagger\/ssl.swagger.json","id":"ssl.swagger"}]